LICENSE.txt
README.md
setup.py
copspy/__init__.py
copspy/api_urls.py
copspy/apierror.py
copspy/get_profile.py
copspy.egg-info/PKG-INFO
copspy.egg-info/SOURCES.txt
copspy.egg-info/dependency_links.txt
copspy.egg-info/requires.txt
copspy.egg-info/top_level.txt